aws_sqs_consumer/__init__.py
aws_sqs_consumer/consumer.py
aws_sqs_consumer/error.py
aws_sqs_consumer/message.py
aws_sqs_consumer-0.0.15.dist-info/LICENSE
aws_sqs_consumer-0.0.15.dist-info/METADATA
aws_sqs_consumer-0.0.15.dist-info/WHEEL
aws_sqs_consumer-0.0.15.dist-info/RECORD
