Metadata-Version: 2.1
Name: aws-sqs-consumer
Version: 0.0.15
Summary: AWS SQS Consumer
Home-page: https://aws-sqs-consumer-python.readthedocs.io/
License: MIT
Keywords: sqs,aws,sqs-consumer
Author: Hexmos Technology
Author-email: nobody@flyweightgroup.com
Requires-Python: >=3.8,<4.0
Classifier: Development Status :: 4 - Beta
Classifier: License :: OSI Approved :: MIT License
Classifier: Programming Language :: Python :: 3
Classifier: Programming Language :: Python :: 3.8
Classifier: Programming Language :: Python :: 3.9
Classifier: Programming Language :: Python :: 3.10
Classifier: Programming Language :: Python :: 3.11
Classifier: Programming Language :: Python :: 3 :: Only
Classifier: Topic :: Software Development :: Libraries
Requires-Dist: boto3 (>=1.16.0,<2.0.0)
Requires-Dist: botocore (>=1.20.0,<2.0.0)
Requires-Dist: single-source (>=0.2.0,<0.3.0)
Project-URL: Documentation, https://aws-sqs-consumer-python.readthedocs.io/
Project-URL: Repository, https://github.com/HexmosTech/aws_sqs_consumer_python
